neural_dispatch/.gitignore
neural_dispatch/__init__.py
neural_dispatch/router.py
neural_dispatch-0.1.0.dist-info/METADATA
neural_dispatch-0.1.0.dist-info/WHEEL
neural_dispatch-0.1.0.dist-info/licenses/LICENSE
neural_dispatch-0.1.0.dist-info/RECORD
